calculator/__init__.py
calculator/calculator.py
calculator_vg-0.1.0.dist-info/LICENSE
calculator_vg-0.1.0.dist-info/WHEEL
calculator_vg-0.1.0.dist-info/METADATA
calculator_vg-0.1.0.dist-info/RECORD
