Metadata-Version: 2.1
Name: calculator_vg
Version: 0.1.0
Summary: Simple calculator.
Author-email: Vilmantas Gegzna <GegznaV@gmail.com>
Classifier: License :: OSI Approved :: MIT License
Project-URL: Home, https://github.com/gegznav/calculator-py
